[
  {
    "name": "scenescript",
    "displayName": "SceneScript",
    "dbdName": "SceneScript.dbd",
    "dbdUrl": "https://raw.githubusercontent.com/wowdev/WoWDBDefs/master/definitions/SceneScript.dbd",
    "layoutHashes": []
  },
  {
    "name": "battlepetspecies",
    "displayName": "BattlePetSpecies",
    "dbdName": "BattlePetSpecies.dbd",
    "dbdUrl": "https://raw.githubusercontent.com/wowdev/WoWDBDefs/master/definitions/BattlePetSpecies.dbd",
    "layoutHashes": []
  },
  {
    "name": "worldelapsedtimer",
    "displayName": "WorldElapsedTimer",
    "dbdName": "WorldElapsedTimer.dbd",
    "dbdUrl": "https://raw.githubusercontent.com/wowdev/WoWDBDefs/master/definitions/WorldElapsedTimer.dbd",
    "layoutHashes": []
  },
  {
    "name": "spellreagents",
    "displayName": "SpellReagents",
    "dbdName": "SpellReagents.dbd",
    "dbdUrl": "https://raw.githubusercontent.com/wowdev/WoWDBDefs/master/definitions/SpellReagents.dbd",
    "layoutHashes": []
  },
  {
    "name": "scenescriptpackagemember",
    "displayName": "SceneScriptPackageMember",
    "dbdName": "SceneScriptPackageMember.dbd",
    "dbdUrl": "https://raw.githubusercontent.com/wowdev/WoWDBDefs/master/definitions/SceneScriptPackageMember.dbd",
    "layoutHashes": []
  },
  {
    "name": "battlepetability",
    "displayName": "BattlePetAbility",
    "dbdName": "BattlePetAbility.dbd",
    "dbdUrl": "https://raw.githubusercontent.com/wowdev/WoWDBDefs/master/definitions/BattlePetAbility.dbd",
    "layoutHashes": []
  },
  {
    "name": "lfgdungeons",
    "displayName": "LFGDungeons",
    "dbdName": "LFGDungeons.dbd",
    "dbdUrl": "https://raw.githubusercontent.com/wowdev/WoWDBDefs/master/definitions/LFGDungeons.dbd",
    "layoutHashes": []
  }
]